pyfuzon-0.4.0.dist-info/METADATA
pyfuzon-0.4.0.dist-info/WHEEL
pyfuzon.libs/libgcc_s-e52197c3.so.1
pyfuzon/__init__.py
pyfuzon/cache.py
pyfuzon/matcher.py
pyfuzon/pyfuzon.abi3.so
pyfuzon-0.4.0.dist-info/RECORD
